hieroglyph/__init__.py
hieroglyph/_version.py
hieroglyph/builder.py
hieroglyph/directives.py
hieroglyph/html.py
hieroglyph/quickstart.py
hieroglyph/slides.py
hieroglyph/themes.py
hieroglyph/writer.py
hieroglyph/tests/__init__.py
hieroglyph/tests/test_builder.py
hieroglyph/tests/test_directives.py
hieroglyph/tests/test_event_handlers.py
hieroglyph/tests/test_path_fixing.py
hieroglyph/tests/test_quickstart.py
hieroglyph/tests/test_slide_footer.py
hieroglyph/tests/test_translator.py
hieroglyph/tests/util.py
hieroglyph/themes/default/prettify.js
hieroglyph/themes/default/slides.js
hieroglyph/themes/default/styles.css
hieroglyph/themes/default/theme.css
hieroglyph/themes/default/images/colorbar.png
hieroglyph/themes/default/images/google-logo-small.png
hieroglyph/themes/default/images/google-logo.png
hieroglyph/themes/default/images/googleio-logo.png
hieroglyph/themes/inline-slides/static/slides.css
hieroglyph/themes/inline-slides/static/fonts/droidsansmono-webfont.eot
hieroglyph/themes/inline-slides/static/fonts/droidsansmono-webfont.svg
hieroglyph/themes/inline-slides/static/fonts/droidsansmono-webfont.ttf
hieroglyph/themes/inline-slides/static/fonts/droidsansmono-webfont.woff
hieroglyph/themes/inline-slides/static/fonts/generator_config.txt
hieroglyph/themes/inline-slides/static/fonts/opensans-italic-webfont.eot
hieroglyph/themes/inline-slides/static/fonts/opensans-italic-webfont.svg
hieroglyph/themes/inline-slides/static/fonts/opensans-italic-webfont.ttf
hieroglyph/themes/inline-slides/static/fonts/opensans-italic-webfont.woff
hieroglyph/themes/inline-slides/static/fonts/opensans-light-webfont.eot
hieroglyph/themes/inline-slides/static/fonts/opensans-light-webfont.svg
hieroglyph/themes/inline-slides/static/fonts/opensans-light-webfont.ttf
hieroglyph/themes/inline-slides/static/fonts/opensans-light-webfont.woff
hieroglyph/themes/inline-slides/static/fonts/opensans-lightitalic-webfont.eot
hieroglyph/themes/inline-slides/static/fonts/opensans-lightitalic-webfont.svg
hieroglyph-2.1.0.dist-info/LICENSE
hieroglyph-2.1.0.dist-info/METADATA
hieroglyph-2.1.0.dist-info/WHEEL
hieroglyph-2.1.0.dist-info/entry_points.txt
hieroglyph-2.1.0.dist-info/top_level.txt
hieroglyph-2.1.0.dist-info/RECORD
