Metadata-Version: 2.1
Name: hieroglyph
Version: 2.1.0
Summary: Generate HTML presentations from plain text sources with all the power of Sphinx.
Home-page: https://github.com/nyergler/hieroglyph
Author: Nathan Yergler
Author-email: nathan@yergler.net
License: BSD
Platform: UNKNOWN
Classifier: License :: OSI Approved :: BSD License
Classifier: Topic :: Documentation
Classifier: Topic :: Text Processing
Classifier: Programming Language :: Python :: 3
Requires-Dist: setuptools
Requires-Dist: Sphinx (>=2.0)
